{
    toast: {
        size: {
            container: {
                width: { comment: 'DEPRECATED: `component` token will be removed - use `global` token or raw value', value: '360px'},
                border: {
                    radius: { comment: 'DEPRECATED: `component` token will be removed - use `global` token or raw value', value: '{size.s}'}
                },
                padding: {
                    left: { comment: 'DEPRECATED: `component` token will be removed - use `global` token or raw value', value: '{size.m}' },
                    right: { comment: 'DEPRECATED: `component` token will be removed - use `global` token or raw value', value: '{size.s}' },
                }
            },
            // центральная область, в которой расположены текст и кнопки
            content: {
                padding: {
                    top: { comment: 'DEPRECATED: `component` token will be removed - use `global` token or raw value', value: '{size.l}' },
                    bottom: { comment: 'DEPRECATED: `component` token will be removed - use `global` token or raw value', value: '{size.l}' }
                }
            },
            caption: {
                padding: {
                    bottom: { comment: 'DEPRECATED: `component` token will be removed - use `global` token or raw value', value: '{size.xxs}' }
                }
            },
            icon: {
                //обертка вокруг иконик, например захотим поместить иконку в кружок
                // сейчас
                width: { comment: 'DEPRECATED: `component` token will be removed - use `global` token or raw value', value: '{size.l}' },
                height: { comment: 'DEPRECATED: `component` token will be removed - use `global` token or raw value', value: '{size.l}' },
                margin: {
                    right: { comment: 'DEPRECATED: `component` token will be removed - use `global` token or raw value', value: '{size.s}' },
                },
                'border-radius': { comment: 'DEPRECATED: `component` token will be removed - use `global` token or raw value', value: '50%' }
            },
            'close-button': {
                margin: {
                    top: { comment: 'DEPRECATED: `component` token will be removed - use `global` token or raw value', value: '{size.m}' },
                    right: { comment: 'DEPRECATED: `component` token will be removed - use `global` token or raw value', value: '{size.xxs}' }
                }
            },
            'button-stack': {
                padding: {
                    top: { comment: 'DEPRECATED: `component` token will be removed - use `global` token or raw value', value: '{size.s}' }
                },
                'content-gap': {
                    horizontal: { comment: 'DEPRECATED: `component` token will be removed - use `global` token or raw value', value: '{size.m}'}
                }
            }
        },
        font: {
            title: {
                "font-size": { comment: 'DEPRECATED: `component` token will be removed - use `global` token or raw value', value: '{typography.text-normal.font-size}' },
                "line-height": { comment: 'DEPRECATED: `component` token will be removed - use `global` token or raw value', value: '{typography.text-normal.line-height}' },
                "letter-spacing": { comment: 'DEPRECATED: `component` token will be removed - use `global` token or raw value', value: '{typography.text-normal.letter-spacing}' },
                "font-weight": { comment: 'DEPRECATED: `component` token will be removed - use `global` token or raw value', value: '{typography.text-normal.font-weight}' },
                "font-family": { comment: 'DEPRECATED: `component` token will be removed - use `global` token or raw value', value: '{typography.text-normal.font-family}' },
                "text-transform": { comment: 'DEPRECATED: `component` token will be removed - use `global` token or raw value', value: '{typography.text-normal.text-transform}' },
                "font-feature-settings": { comment: 'DEPRECATED: `component` token will be removed - use `global` token or raw value', value: '{typography.text-normal.font-feature-settings}' }
            },
            text: {
                "font-size": { comment: 'DEPRECATED: `component` token will be removed - use `global` token or raw value', value: '{typography.text-normal.font-size}' },
                "line-height": { comment: 'DEPRECATED: `component` token will be removed - use `global` token or raw value', value: '{typography.text-normal.line-height}' },
                "letter-spacing": { comment: 'DEPRECATED: `component` token will be removed - use `global` token or raw value', value: '{typography.text-normal.letter-spacing}' },
                "font-weight": { comment: 'DEPRECATED: `component` token will be removed - use `global` token or raw value', value: '{typography.text-normal.font-weight}' },
                "font-family": { comment: 'DEPRECATED: `component` token will be removed - use `global` token or raw value', value: '{typography.text-normal.font-family}' },
                "text-transform": { comment: 'DEPRECATED: `component` token will be removed - use `global` token or raw value', value: '{typography.text-normal.text-transform}' },
                "font-feature-settings": { comment: 'DEPRECATED: `component` token will be removed - use `global` token or raw value', value: '{typography.text-normal.font-feature-settings}' }
            }
        },
        'light': {
            contrast: {
                container: {
                    background: { comment: 'DEPRECATED: `component` token will be removed - use `global` token or raw value', value: '{light.background.card}' },
                    title: { comment: 'DEPRECATED: `component` token will be removed - use `global` token or raw value', value: '{light.foreground.contrast}' },
                    text: { comment: 'DEPRECATED: `component` token will be removed - use `global` token or raw value', value: '{light.foreground.contrast-secondary}' },
                    shadow: { comment: 'DEPRECATED: `component` token will be removed - use `global` token or raw value', value: '{shadow.light.popup}'}
                }
            },
            error: {
                container: {
                    background: { comment: 'DEPRECATED: `component` token will be removed - use `global` token or raw value', value: '{light.background.card}' },
                    title: { comment: 'DEPRECATED: `component` token will be removed - use `global` token or raw value', value: '{light.foreground.contrast}' },
                    text: { comment: 'DEPRECATED: `component` token will be removed - use `global` token or raw value', value: '{light.foreground.contrast-secondary}' },
                    shadow: { comment: 'DEPRECATED: `component` token will be removed - use `global` token or raw value', value: '{shadow.light.popup}'}
                }
            },
            warning: {
                container: {
                    background: { comment: 'DEPRECATED: `component` token will be removed - use `global` token or raw value', value: '{light.background.card}' },
                    title: { comment: 'DEPRECATED: `component` token will be removed - use `global` token or raw value', value: '{light.foreground.contrast}' },
                    text: { comment: 'DEPRECATED: `component` token will be removed - use `global` token or raw value', value: '{light.foreground.contrast-secondary}' },
                    shadow: { comment: 'DEPRECATED: `component` token will be removed - use `global` token or raw value', value: '{shadow.light.popup}'}
                }
            },
            success: {
                container: {
                    background: { comment: 'DEPRECATED: `component` token will be removed - use `global` token or raw value', value: '{light.background.card}' },
                    title: { comment: 'DEPRECATED: `component` token will be removed - use `global` token or raw value', value: '{light.foreground.contrast}' },
                    text: { comment: 'DEPRECATED: `component` token will be removed - use `global` token or raw value', value: '{light.foreground.contrast-secondary}' },
                    shadow: { comment: 'DEPRECATED: `component` token will be removed - use `global` token or raw value', value: '{shadow.light.popup}'}
                }
            }
        },
        'dark': {
            contrast: {
                container: {
                    background: { comment: 'DEPRECATED: `component` token will be removed - use `global` token or raw value', value: '{dark.background.card}' },
                    title: { comment: 'DEPRECATED: `component` token will be removed - use `global` token or raw value', value: '{dark.foreground.contrast}' },
                    text: { comment: 'DEPRECATED: `component` token will be removed - use `global` token or raw value', value: '{dark.foreground.contrast-secondary}' },
                    shadow: { comment: 'DEPRECATED: `component` token will be removed - use `global` token or raw value', value: '{shadow.dark.popup}'}
                }
            },
            error: {
                container: {
                    background: { comment: 'DEPRECATED: `component` token will be removed - use `global` token or raw value', value: '{dark.background.card}' },
                    title: { comment: 'DEPRECATED: `component` token will be removed - use `global` token or raw value', value: '{dark.foreground.contrast}' },
                    text: { comment: 'DEPRECATED: `component` token will be removed - use `global` token or raw value', value: '{dark.foreground.contrast-secondary}' },
                    shadow: { comment: 'DEPRECATED: `component` token will be removed - use `global` token or raw value', value: '{shadow.dark.popup}'}
                }
            },
            warning: {
                container: {
                    background: { comment: 'DEPRECATED: `component` token will be removed - use `global` token or raw value', value: '{dark.background.card}' },
                    title: { comment: 'DEPRECATED: `component` token will be removed - use `global` token or raw value', value: '{dark.foreground.contrast}' },
                    text: { comment: 'DEPRECATED: `component` token will be removed - use `global` token or raw value', value: '{dark.foreground.contrast-secondary}' },
                    shadow: { comment: 'DEPRECATED: `component` token will be removed - use `global` token or raw value', value: '{shadow.dark.popup}'}
                }
            },
            success: {
                container: {
                    background: { comment: 'DEPRECATED: `component` token will be removed - use `global` token or raw value', value: '{dark.background.card}' },
                    title: { comment: 'DEPRECATED: `component` token will be removed - use `global` token or raw value', value: '{dark.foreground.contrast}' },
                    text: { comment: 'DEPRECATED: `component` token will be removed - use `global` token or raw value', value: '{dark.foreground.contrast-secondary}' },
                    shadow: { comment: 'DEPRECATED: `component` token will be removed - use `global` token or raw value', value: '{shadow.dark.popup}'}
                }
            }
        }
    },
    'toast-stack': {
        size: {
            margin: {
                top: { comment: 'DEPRECATED: `component` token will be removed - use `global` token or raw value', value: '{size.m}' },
                right: { comment: 'DEPRECATED: `component` token will be removed - use `global` token or raw value', value: '{size.m}' }
            },
            gap: { comment: 'DEPRECATED: `component` token will be removed - use `global` token or raw value', value: '{size.s}' }
        }
    }
}
